LICENSE
MANIFEST.in
README.rst
setup.py
bootstrap/__init__.py
bootstrap/admin.py
bootstrap/forms.py
bootstrap/helpers.py
bootstrap/manage.py
bootstrap/models.py
bootstrap/tests.py
bootstrap/urls.py
bootstrap/views.py
bootstrap/widgets.py
bootstrap/static/.DS_Store
bootstrap/static/.gitkeep
bootstrap/static/admin/.DS_Store
bootstrap/static/admin/css/.DS_Store
bootstrap/static/admin/css/bootstrap.css
bootstrap/static/admin/css/chosen-sprite.png
bootstrap/static/admin/css/chosen.css
bootstrap/static/admin/css/custom.css
bootstrap/static/admin/css/flat-ui.css
bootstrap/static/admin/css/screen.css
bootstrap/static/admin/img/glyphicons-halflings-white.png
bootstrap/static/admin/img/glyphicons-halflings.png
bootstrap/static/admin/img/defaults/460x170.jpg
bootstrap/static/admin/img/defaults/960x410.jpg
bootstrap/static/admin/js/.DS_Store
bootstrap/static/admin/js/bootstrap.min.js
bootstrap/static/admin/js/chosen.jquery.min.js
bootstrap/static/admin/js/forms.js
bootstrap/static/admin/js/jquery-1.8.2.min.js
bootstrap/static/admin/js/jquery-ui-1.8.24.custom.min.js
bootstrap/static/admin/js/jquery.csrftoken.js
bootstrap/static/admin/js/jquery.gritter.min.js
bootstrap/static/admin/js/sort.js
bootstrap/static/admin/js/wysihtml5/dist/wysihtml5-0.2.0.js
bootstrap/static/admin/js/wysihtml5/dist/wysihtml5-0.2.0.min.js
bootstrap/static/admin/js/wysihtml5/dist/wysihtml5-0.3.0.js
bootstrap/static/admin/js/wysihtml5/dist/wysihtml5-0.3.0.min.js
bootstrap/static/admin/js/wysihtml5/dist/wysihtml5-0.4.0pre.js
bootstrap/static/admin/js/wysihtml5/dist/wysihtml5-0.4.0pre.min.js
bootstrap/static/admin/js/wysihtml5/parser_rules/advanced.js
bootstrap/static/admin/js/wysihtml5/parser_rules/simple.js
bootstrap/templates/admin/.DS_Store
bootstrap/templates/admin/404.html
bootstrap/templates/admin/500.html
bootstrap/templates/admin/actions.html
bootstrap/templates/admin/app_index.html
bootstrap/templates/admin/base.html
bootstrap/templates/admin/base_site.html
django_bootstrap_admin.egg-info/PKG-INFO
django_bootstrap_admin.egg-info/SOURCES.txt
django_bootstrap_admin.egg-info/dependency_links.txt
django_bootstrap_admin.egg-info/top_level.txt