Metadata-Version: 1.0
Name: django-bootstrap-admin
Version: 0.3.2
Summary: Adds twitter bootstrap and other nicities to the Django admin
Home-page: http://github.com/maxfolley/django-bootstrap-admin
Author: Maxwell Folley
Author-email: maxwell@weareflavor.com
License: MIT License
Platform: UNKNOWN
Classifier: Environment :: Web Environment
Classifier: Framework :: Django
Classifier: Intended Audience :: Developers
Classifier: License :: OSI Approved :: MIT License
Classifier: Operating System :: OS Independent
Classifier: Programming Language :: Python
Classifier: Programming Language :: Python :: 2.7
Classifier: Topic :: Internet :: WWW/HTTP
Classifier: Topic :: Internet :: WWW/HTTP :: Dynamic Content
